[{"id":"IXP_1306","name":"NAPAfrica Johannesburg","country":"ZAF","latitude":-26.64177445933199,"longitude":29.76421154007879,"customers":"ASN_11744_ZAF,ASN_37187_MWI,ASN_32934_ZAF,ASN_49544_ZAF,ASN_21739_ZAF,ASN_24691_TGO,ASN_37356_ZAF,ASN_7020_ZAF,ASN_54113_ZAF,ASN_37053_ZAF,ASN_33764_MUS,ASN_33764_ZAF,ASN_6968_ZAF,ASN_327826_ZAF,ASN_37596_ZAF,ASN_37271_ZAF,ASN_4134_ZAF,ASN_37153_ZAF,ASN_37153_SYC,ASN_6083_ZAF,ASN_37105_ZAF,ASN_37678_BWA,ASN_29918_ZAF,ASN_22355_ZAF,ASN_37403_ZAF,ASN_37172_ZAF,ASN_37349_TZA,ASN_37622_MUS,ASN_37447_COD,ASN_37183_ZAF,ASN_37183_ZWE,ASN_37183_UGA,ASN_14115_ZAF,ASN_37491_ZAF,ASN_3257_ZAF,ASN_30999_MUS,ASN_36692_ZAF,ASN_21859_ZAF,ASN_21859_NGA,ASN_3300_ZAF,ASN_36919_ZAF,ASN_37468_AGO,ASN_37675_ZAF,ASN_3067_ZAF,ASN_37007_ZAF,ASN_21351_REU,ASN_15133_ZAF,ASN_37439_ZAF,ASN_10310_ZAF,ASN_37204_ZWE,ASN_37525_ZAF,ASN_22822_ZAF,ASN_37342_MOZ,ASN_37564_ZAF,ASN_54994_ZAF,ASN_327849_ZAF,ASN_37016_ZAF,ASN_16509_ZAF,ASN_5713_ZAF,ASN_5713_KEN,ASN_37670_ZAF,ASN_37054_MDG,ASN_37484_ZAF,ASN_327897_ZAF,ASN_37157_ZAF,ASN_327811_ZAF,ASN_10474_ZAF,ASN_327824_ZAF,ASN_15695_MAR,ASN_41095_SYC,ASN_327893_ZAF,ASN_3741_ZAF,ASN_3741_SYC,ASN_37658_ZAF,ASN_8075_ZAF,ASN_22572_ZAF,ASN_32653_ZAF,ASN_33763_NAM,ASN_33763_AGO,ASN_33763_MOZ,ASN_37627_ZAF,ASN_37168_ZAF,ASN_36236_ZAF,ASN_37225_ZAF,ASN_44444_ZAF,ASN_44444_CIV,ASN_44444_DZA,ASN_44444_GHA,ASN_44444_MAR,ASN_44444_TUN,ASN_44444_MUS,ASN_44444_ETH,ASN_44444_NGA,ASN_44444_KEN,ASN_44444_LBR,ASN_44444_EGY,ASN_44444_AGO,ASN_37302_ZAF,ASN_37314_ZAF,ASN_37179_ZAF,ASN_327767_ZAF,ASN_27471_ZAF,ASN_37358_ZAF,ASN_714_ZAF,ASN_37315_ZAF,ASN_37488_ZAF,ASN_36916_ZAF,ASN_36916_BEN,ASN_37680_ZAF,ASN_327754_ZAF,ASN_37028_ZAF,ASN_37236_ZAF,ASN_55256_ZAF,ASN_36951_ZAF,ASN_37254_ZAF,ASN_42_ZAF,ASN_42_TUN,ASN_37497_ZAF,ASN_19551_ZAF,ASN_199524_ZAF,ASN_37239_ZAF,ASN_37239_BDI,ASN_25818_ZAF,ASN_25818_KEN,ASN_36994_ZAF,ASN_36994_AGO,ASN_36994_NGA,ASN_37049_ZAF,ASN_37009_NAM,ASN_1828_ZAF,ASN_37640_ZAF,ASN_37599_ZAF,ASN_16637_ZAF,ASN_16637_LBR,ASN_16637_MUS,ASN_16637_NAM,ASN_16637_BWA,ASN_16637_ZMB,ASN_37479_ZAF,ASN_20940_ZAF,ASN_3356_ZAF,ASN_3356_NGA,ASN_11845_ZAF,ASN_30844_MUS,ASN_30844_ZMB,ASN_30844_KEN,ASN_30844_TZA,ASN_30844_UGA,ASN_30844_ZAF,ASN_30844_ZWE,ASN_30844_RWA,ASN_30844_COD,ASN_2018_ZAF,ASN_2018_LSO,ASN_37618_ZAF,ASN_37650_ZAF,ASN_37653_ZAF,ASN_327693_ZAF,ASN_37451_COG,ASN_37417_ZAF,ASN_10798_ZAF,ASN_37266_ZAF,ASN_36868_MUS,ASN_36944_ZAF,ASN_37662_DJI,ASN_37662_NGA,ASN_37662_TZA,ASN_37662_ZAF,ASN_37662_MUS,ASN_37662_KEN,ASN_37662_SOM,ASN_37662_ZWE,ASN_37402_ZAF,ASN_36937_ZAF,ASN_327745_ZAF,ASN_36985_ZAF,ASN_327733_ZAF,ASN_37457_ZAF,ASN_327751_ZAF,ASN_327698_ZAF,ASN_36874_ZAF,ASN_327750_COD,ASN_327750_ZAF,ASN_37656_ZAF,ASN_327822_ZAF,ASN_327850_ZAF,ASN_32437_ZAF,ASN_2635_ZAF,ASN_23889_MUS,ASN_23889_ZAF,ASN_4809_NGA,ASN_4809_ZAF,ASN_4809_KEN,ASN_29606_ZAF,ASN_37312_ZAF,ASN_36968_ZAF,ASN_37294_MWI,ASN_37199_ZAF,ASN_19711_SWZ,ASN_327872_ZAF,ASN_37542_ZAF,ASN_37035_TZA,ASN_14988_BWA,ASN_14988_ZAF,ASN_14988_CIV,ASN_327812_ZAF,ASN_42473_ZAF,ASN_37154_ZMB,ASN_37482_ZAF,ASN_15022_ZAF,ASN_37055_ZAF,ASN_37634_ZAF,ASN_37276_ZAF,ASN_37363_ZAF,ASN_327894_ZAF,ASN_198949_MOZ,ASN_198949_MAR,ASN_33781_BWA,ASN_37628_ZAF,ASN_327808_ZAF,ASN_327791_ZAF,ASN_37368_ZAF,ASN_327761_ZAF,ASN_3491_ZAF,ASN_3491_KEN,ASN_3491_TZA,ASN_3491_MOZ,ASN_3491_ZMB,ASN_3491_TUN,ASN_37079_ZAF,ASN_37519_ZAF,ASN_327813_GHA,ASN_327813_ZAF,ASN_327813_NGA,ASN_327813_KEN,ASN_327813_SYC,ASN_37549_ZAF,ASN_26106_ZAF,ASN_37150_ZAF,ASN_37100_KEN,ASN_37100_MUS,ASN_37100_TZA,ASN_37100_ZAF,ASN_327782_ZAF,ASN_13335_REU,ASN_13335_ZAF,ASN_13335_RWA,ASN_13335_DJI,ASN_13335_MAR,ASN_13335_NGA,ASN_13335_TZA,ASN_13335_KEN,ASN_13335_MDG,ASN_13335_AGO,ASN_13335_MUS,ASN_37395_BWA,ASN_37523_ZAF,ASN_37652_ZAF,ASN_37673_ZAF,ASN_327804_ZAF,ASN_11179_ZAF,ASN_327892_ZAF,ASN_37399_ZAF,ASN_327737_ZAF,ASN_37546_BWA,ASN_37546_ZAF,ASN_40676_ZAF,ASN_327716_BWA,ASN_37317_ZAF,ASN_37002_REU,ASN_37333_ZAF,ASN_37697_MOZ,ASN_37412_ZAF,ASN_37438_ZAF,ASN_62597_ZAF,ASN_61092_ZAF,ASN_327817_ZAF,ASN_60171_MLI,ASN_60171_GHA,ASN_60171_BFA,ASN_60171_NGA,ASN_32398_SWZ"},{"id":"IXP_616","name":"Internet Exchange Point of Nigeria - Lagos","country":"NGA","latitude":8.27335090043718,"longitude":3.6040161202380867,"customers":"ASN_42_ZAF,ASN_42_TUN,ASN_327813_GHA,ASN_327813_ZAF,ASN_327813_NGA,ASN_327813_KEN,ASN_327813_SYC,ASN_32934_ZAF,ASN_21859_ZAF,ASN_21859_NGA,ASN_37468_AGO,ASN_13335_REU,ASN_13335_ZAF,ASN_13335_RWA,ASN_13335_DJI,ASN_13335_MAR,ASN_13335_NGA,ASN_13335_TZA,ASN_13335_KEN,ASN_13335_MDG,ASN_13335_AGO,ASN_13335_MUS,ASN_8075_ZAF,ASN_37662_DJI,ASN_37662_NGA,ASN_37662_TZA,ASN_37662_ZAF,ASN_37662_MUS,ASN_37662_KEN,ASN_37662_SOM,ASN_37662_ZWE,ASN_3491_ZAF,ASN_3491_KEN,ASN_3491_TZA,ASN_3491_MOZ,ASN_3491_ZMB,ASN_3491_TUN,ASN_36932_NGA,ASN_36938_NGA,ASN_37629_NGA,ASN_37148_NGA,ASN_37148_GHA,ASN_37637_NGA,ASN_37308_NGA,ASN_37088_NGA,ASN_36920_NGA"},{"id":"IXP_1308","name":"NAPAfrica Cape Town","country":"ZAF","latitude":-34.0228037627129,"longitude":18.503288381747897,"customers":"ASN_3491_ZAF,ASN_3491_KEN,ASN_3491_TZA,ASN_3491_MOZ,ASN_3491_ZMB,ASN_3491_TUN,ASN_37105_ZAF,ASN_36994_ZAF,ASN_36994_AGO,ASN_36994_NGA,ASN_42_ZAF,ASN_42_TUN,ASN_11845_ZAF,ASN_327693_ZAF,ASN_37271_ZAF,ASN_37153_ZAF,ASN_37153_SYC,ASN_37239_ZAF,ASN_37239_BDI,ASN_37363_ZAF,ASN_37599_ZAF,ASN_37457_ZAF,ASN_8075_ZAF,ASN_327804_ZAF,ASN_37009_NAM,ASN_37640_ZAF,ASN_36874_ZAF,ASN_16637_ZAF,ASN_16637_LBR,ASN_16637_MUS,ASN_16637_NAM,ASN_16637_BWA,ASN_16637_ZMB,ASN_37100_KEN,ASN_37100_MUS,ASN_37100_TZA,ASN_37100_ZAF,ASN_2018_ZAF,ASN_2018_LSO,ASN_37439_ZAF,ASN_15022_ZAF,ASN_37254_ZAF,ASN_327872_ZAF,ASN_22355_ZAF,ASN_37199_ZAF,ASN_37542_ZAF,ASN_327733_ZAF,ASN_37691_ZAF,ASN_54113_ZAF,ASN_16509_ZAF,ASN_20940_ZAF,ASN_37670_ZAF,ASN_327849_ZAF,ASN_327824_ZAF,ASN_32653_ZAF,ASN_10474_ZAF,ASN_37314_ZAF,ASN_37172_ZAF,ASN_37468_AGO,ASN_327754_ZAF,ASN_37236_ZAF,ASN_25818_ZAF,ASN_25818_KEN,ASN_327782_ZAF,ASN_37049_ZAF,ASN_13335_REU,ASN_13335_ZAF,ASN_13335_RWA,ASN_13335_DJI,ASN_13335_MAR,ASN_13335_NGA,ASN_13335_TZA,ASN_13335_KEN,ASN_13335_MDG,ASN_13335_AGO,ASN_13335_MUS,ASN_30844_MUS,ASN_30844_ZMB,ASN_30844_KEN,ASN_30844_TZA,ASN_30844_UGA,ASN_30844_ZAF,ASN_30844_ZWE,ASN_30844_RWA,ASN_30844_COD,ASN_37662_DJI,ASN_37662_NGA,ASN_37662_TZA,ASN_37662_ZAF,ASN_37662_MUS,ASN_37662_KEN,ASN_37662_SOM,ASN_37662_ZWE,ASN_54994_ZAF,ASN_37179_ZAF,ASN_327822_ZAF,ASN_36916_ZAF,ASN_36916_BEN,ASN_36943_ZAF,ASN_37225_ZAF,ASN_37479_ZAF,ASN_29606_ZAF,ASN_37312_ZAF,ASN_7020_ZAF,ASN_37053_ZAF,ASN_37315_ZAF,ASN_36898_ZAF,ASN_33763_NAM,ASN_33763_AGO,ASN_33763_MOZ,ASN_37266_ZAF,ASN_37358_ZAF,ASN_3356_ZAF,ASN_3356_NGA,ASN_37497_ZAF,ASN_37628_ZAF,ASN_37150_ZAF,ASN_37399_ZAF,ASN_36968_ZAF,ASN_327698_ZAF,ASN_37417_ZAF,ASN_37652_ZAF,ASN_37656_ZAF,ASN_37333_ZAF,ASN_327772_ZAF,ASN_327750_COD,ASN_327750_ZAF,ASN_3067_ZAF,ASN_61092_ZAF,ASN_327812_ZAF,ASN_37678_BWA,ASN_327897_ZAF,ASN_3741_ZAF,ASN_3741_SYC,ASN_37564_ZAF,ASN_37482_ZAF,ASN_37680_ZAF,ASN_14115_ZAF,ASN_5713_ZAF,ASN_5713_KEN,ASN_37549_ZAF,ASN_26106_ZAF,ASN_37168_ZAF,ASN_37675_ZAF,ASN_37525_ZAF,ASN_37130_ZAF,ASN_37634_ZAF,ASN_32437_ZAF,ASN_37673_ZAF,ASN_37627_ZAF,ASN_37276_ZAF,ASN_36937_ZAF,ASN_37546_BWA,ASN_37546_ZAF,ASN_327751_ZAF"},{"id":"IXP_209","name":"Johannesburg Internet Exchange","country":"ZAF","latitude":-25.03561798681656,"longitude":27.844266418211646,"customers":"ASN_37474_ZAF,ASN_3741_ZAF,ASN_3741_SYC,ASN_42_ZAF,ASN_42_TUN,ASN_16637_ZAF,ASN_16637_LBR,ASN_16637_MUS,ASN_16637_NAM,ASN_16637_BWA,ASN_16637_ZMB,ASN_11845_ZAF,ASN_6083_ZAF,ASN_36937_ZAF,ASN_10474_ZAF,ASN_6968_ZAF,ASN_2018_ZAF,ASN_2018_LSO,ASN_15022_ZAF,ASN_32653_ZAF,ASN_36874_ZAF,ASN_37105_ZAF,ASN_37640_ZAF,ASN_37179_ZAF,ASN_30844_MUS,ASN_30844_ZMB,ASN_30844_KEN,ASN_30844_TZA,ASN_30844_UGA,ASN_30844_ZAF,ASN_30844_ZWE,ASN_30844_RWA,ASN_30844_COD,ASN_33764_MUS,ASN_33764_ZAF,ASN_37271_ZAF,ASN_33763_NAM,ASN_33763_AGO,ASN_33763_MOZ,ASN_327872_ZAF,ASN_22355_ZAF,ASN_37159_ZAF,ASN_37235_ZAF,ASN_37236_ZAF,ASN_327782_ZAF,ASN_37356_ZAF,ASN_37172_ZAF,ASN_44444_ZAF,ASN_44444_CIV,ASN_44444_DZA,ASN_44444_GHA,ASN_44444_MAR,ASN_44444_TUN,ASN_44444_MUS,ASN_44444_ETH,ASN_44444_NGA,ASN_44444_KEN,ASN_44444_LBR,ASN_44444_EGY,ASN_44444_AGO,ASN_37100_KEN,ASN_37100_MUS,ASN_37100_TZA,ASN_37100_ZAF,ASN_37670_ZAF,ASN_37153_ZAF,ASN_37153_SYC,ASN_37150_ZAF,ASN_37399_ZAF,ASN_13335_REU,ASN_13335_ZAF,ASN_13335_RWA,ASN_13335_DJI,ASN_13335_MAR,ASN_13335_NGA,ASN_13335_TZA,ASN_13335_KEN,ASN_13335_MDG,ASN_13335_AGO,ASN_13335_MUS,ASN_37542_ZAF,ASN_37314_ZAF,ASN_37678_BWA,ASN_36916_ZAF,ASN_36916_BEN,ASN_4809_NGA,ASN_4809_ZAF,ASN_4809_KEN,ASN_36968_ZAF,ASN_32437_ZAF,ASN_327849_ZAF,ASN_327733_ZAF,ASN_49544_ZAF,ASN_327813_GHA,ASN_327813_ZAF,ASN_327813_NGA,ASN_327813_KEN,ASN_327813_SYC,ASN_327817_ZAF,ASN_37049_ZAF,ASN_37177_ZAF,ASN_37181_ZAF,ASN_37439_ZAF,ASN_26422_ZAF,ASN_33762_ZAF,ASN_4134_ZAF,ASN_26106_ZAF,ASN_37315_ZAF,ASN_37053_ZAF,ASN_7020_ZAF,ASN_37546_BWA,ASN_37546_ZAF,ASN_22750_ZAF,ASN_37157_ZAF,ASN_37525_ZAF,ASN_37168_ZAF,ASN_37333_ZAF,ASN_36868_MUS,ASN_36994_ZAF,ASN_36994_AGO,ASN_36994_NGA,ASN_37358_ZAF,ASN_37680_ZAF,ASN_37549_ZAF,ASN_37497_ZAF,ASN_37650_ZAF,ASN_327893_ZAF,ASN_715_ZAF,ASN_715_MUS,ASN_715_EGY,ASN_19711_SWZ,ASN_37317_ZAF,ASN_8075_ZAF,ASN_55256_ZAF,ASN_40676_ZAF"},{"id":"IXP_1362","name":"Durban Internet eXchange","country":"ZAF","latitude":-29.1486129473103,"longitude":30.73964113069875,"customers":"ASN_3741_ZAF,ASN_3741_SYC,ASN_5713_ZAF,ASN_5713_KEN,ASN_42_ZAF,ASN_42_TUN,ASN_11845_ZAF,ASN_33762_ZAF,ASN_10474_ZAF,ASN_2018_ZAF,ASN_2018_LSO,ASN_37315_ZAF,ASN_32653_ZAF,ASN_36874_ZAF,ASN_37179_ZAF,ASN_36916_ZAF,ASN_36916_BEN,ASN_37457_ZAF,ASN_37271_ZAF,ASN_36994_ZAF,ASN_36994_AGO,ASN_36994_NGA,ASN_37172_ZAF,ASN_37358_ZAF,ASN_37100_KEN,ASN_37100_MUS,ASN_37100_TZA,ASN_37100_ZAF,ASN_37680_ZAF,ASN_37497_ZAF,ASN_327698_ZAF,ASN_13335_REU,ASN_13335_ZAF,ASN_13335_RWA,ASN_13335_DJI,ASN_13335_MAR,ASN_13335_NGA,ASN_13335_TZA,ASN_13335_KEN,ASN_13335_MDG,ASN_13335_AGO,ASN_13335_MUS,ASN_37314_ZAF,ASN_36968_ZAF,ASN_32437_ZAF,ASN_327805_ZAF,ASN_327849_ZAF,ASN_327761_ZAF,ASN_327817_ZAF,ASN_61092_ZAF,ASN_37049_ZAF,ASN_327693_ZAF,ASN_37519_ZAF,ASN_37016_ZAF,ASN_37177_ZAF,ASN_37181_ZAF"},{"id":"IXP_143","name":"Kenya Internet Exchange Point","country":"KEN","latitude":-1.641127405661245,"longitude":35.86971774323492,"customers":"ASN_15399_KEN,ASN_15399_TZA,ASN_15399_UGA,ASN_15399_NGA,ASN_36866_KEN,ASN_15808_KEN,ASN_12455_KEN,ASN_33771_KEN,ASN_36914_KEN,ASN_25568_KEN,ASN_37273_UGA,ASN_12556_KEN,ASN_12556_UGA,ASN_36926_KEN,ASN_36915_KEN,ASN_36948_KEN,ASN_37685_KEN,ASN_37578_KEN,ASN_37684_KEN,ASN_37684_TZA,ASN_37305_KEN,ASN_30844_MUS,ASN_30844_ZMB,ASN_30844_KEN,ASN_30844_TZA,ASN_30844_UGA,ASN_30844_ZAF,ASN_30844_ZWE,ASN_30844_RWA,ASN_30844_COD,ASN_25818_ZAF,ASN_25818_KEN,ASN_42_ZAF,ASN_42_TUN,ASN_37027_KEN,ASN_37027_UGA,ASN_37027_TZA,ASN_37109_KEN,ASN_37271_ZAF,ASN_37619_RWA,ASN_3491_ZAF,ASN_3491_KEN,ASN_3491_TZA,ASN_3491_MOZ,ASN_3491_ZMB,ASN_3491_TUN,ASN_327906_KEN,ASN_37063_UGA,ASN_37662_DJI,ASN_37662_NGA,ASN_37662_TZA,ASN_37662_ZAF,ASN_37662_MUS,ASN_37662_KEN,ASN_37662_SOM,ASN_37662_ZWE,ASN_8075_ZAF,ASN_16509_ZAF,ASN_15133_ZAF,ASN_16637_ZAF,ASN_16637_LBR,ASN_16637_MUS,ASN_16637_NAM,ASN_16637_BWA,ASN_16637_ZMB,ASN_9129_KEN"},{"id":"IXP_206","name":"Cape Town Internet Exchange","country":"ZAF","latitude":-32.83930164225414,"longitude":18.31505968796026,"customers":"ASN_37663_ZAF,ASN_3741_ZAF,ASN_3741_SYC,ASN_11845_ZAF,ASN_36937_ZAF,ASN_10474_ZAF,ASN_16637_ZAF,ASN_16637_LBR,ASN_16637_MUS,ASN_16637_NAM,ASN_16637_BWA,ASN_16637_ZMB,ASN_2018_ZAF,ASN_2018_LSO,ASN_15022_ZAF,ASN_32653_ZAF,ASN_37640_ZAF,ASN_37105_ZAF,ASN_37179_ZAF,ASN_30844_MUS,ASN_30844_ZMB,ASN_30844_KEN,ASN_30844_TZA,ASN_30844_UGA,ASN_30844_ZAF,ASN_30844_ZWE,ASN_30844_RWA,ASN_30844_COD,ASN_37199_ZAF,ASN_37271_ZAF,ASN_327872_ZAF,ASN_37333_ZAF,ASN_22355_ZAF,ASN_37236_ZAF,ASN_37153_ZAF,ASN_37153_SYC,ASN_37150_ZAF,ASN_13335_REU,ASN_13335_ZAF,ASN_13335_RWA,ASN_13335_DJI,ASN_13335_MAR,ASN_13335_NGA,ASN_13335_TZA,ASN_13335_KEN,ASN_13335_MDG,ASN_13335_AGO,ASN_13335_MUS,ASN_37542_ZAF,ASN_327849_ZAF,ASN_20940_ZAF,ASN_37177_ZAF,ASN_37181_ZAF,ASN_42_ZAF,ASN_42_TUN,ASN_33762_ZAF,ASN_37315_ZAF,ASN_37053_ZAF,ASN_36874_ZAF,ASN_36943_ZAF,ASN_36916_ZAF,ASN_36916_BEN,ASN_36994_ZAF,ASN_36994_AGO,ASN_36994_NGA,ASN_37356_ZAF,ASN_37358_ZAF,ASN_37100_KEN,ASN_37100_MUS,ASN_37100_TZA,ASN_37100_ZAF,ASN_37680_ZAF,ASN_37497_ZAF,ASN_36968_ZAF,ASN_32437_ZAF,ASN_16509_ZAF,ASN_8075_ZAF,ASN_37049_ZAF"},{"id":"IXP_479","name":"Kinshasa Internet Exchange","country":"COD","latitude":-3.7193820375191997,"longitude":16.241001747915554,"customers":""},{"id":"IXP_248","name":"Uganda Internet Exchange","country":"UGA","latitude":0.16268858084607163,"longitude":32.750805667129704,"customers":"ASN_37386_UGA,ASN_37063_UGA,ASN_36991_UGA,ASN_30844_MUS,ASN_30844_ZMB,ASN_30844_KEN,ASN_30844_TZA,ASN_30844_UGA,ASN_30844_ZAF,ASN_30844_ZWE,ASN_30844_RWA,ASN_30844_COD,ASN_29039_UGA,ASN_20294_UGA,ASN_21491_UGA,ASN_37113_UGA,ASN_29032_UGA,ASN_37075_UGA,ASN_37610_UGA,ASN_37027_KEN,ASN_37027_UGA,ASN_37027_TZA,ASN_327724_UGA,ASN_37679_UGA,ASN_42_ZAF,ASN_42_TUN,ASN_327687_UGA,ASN_37273_UGA,ASN_37122_UGA,ASN_37122_ZAF,ASN_37100_KEN,ASN_37100_MUS,ASN_37100_TZA,ASN_37100_ZAF,ASN_20940_ZAF,ASN_12491_COD,ASN_12491_UGA,ASN_12491_GAB,ASN_36040_MAR,ASN_12556_KEN,ASN_12556_UGA"},{"id":"IXP_242","name":"TIX Tanzania - Dar es Salaam","country":"TZA","latitude":-9.816349143936428,"longitude":38.98161138654676,"customers":"ASN_33791_TZA,ASN_37126_TZA,ASN_327844_TZA,ASN_327900_TZA,ASN_327859_TZA,ASN_37100_KEN,ASN_37100_MUS,ASN_37100_TZA,ASN_37100_ZAF,ASN_327795_TZA,ASN_37177_ZAF,ASN_37084_TZA,ASN_32860_TZA,ASN_37419_TZA,ASN_37349_TZA,ASN_37045_TZA,ASN_30844_MUS,ASN_30844_ZMB,ASN_30844_KEN,ASN_30844_TZA,ASN_30844_UGA,ASN_30844_ZAF,ASN_30844_ZWE,ASN_30844_RWA,ASN_30844_COD,ASN_20940_ZAF,ASN_36909_TZA,ASN_37181_ZAF,ASN_42_ZAF,ASN_42_TUN,ASN_37474_ZAF,ASN_3741_ZAF,ASN_3741_SYC,ASN_16637_ZAF,ASN_16637_LBR,ASN_16637_MUS,ASN_16637_NAM,ASN_16637_BWA,ASN_16637_ZMB,ASN_11845_ZAF,ASN_6083_ZAF,ASN_36937_ZAF,ASN_10474_ZAF,ASN_6968_ZAF,ASN_2018_ZAF,ASN_2018_LSO,ASN_15022_ZAF,ASN_32653_ZAF,ASN_36874_ZAF,ASN_37105_ZAF,ASN_37640_ZAF,ASN_37179_ZAF,ASN_33764_MUS,ASN_33764_ZAF,ASN_37271_ZAF,ASN_33763_NAM,ASN_33763_AGO,ASN_33763_MOZ,ASN_327872_ZAF,ASN_22355_ZAF,ASN_37159_ZAF,ASN_37235_ZAF,ASN_37236_ZAF,ASN_327782_ZAF,ASN_37356_ZAF,ASN_37172_ZAF,ASN_44444_ZAF,ASN_44444_CIV,ASN_44444_DZA,ASN_44444_GHA,ASN_44444_MAR,ASN_44444_TUN,ASN_44444_MUS,ASN_44444_ETH,ASN_44444_NGA,ASN_44444_KEN,ASN_44444_LBR,ASN_44444_EGY,ASN_44444_AGO,ASN_37670_ZAF,ASN_37153_ZAF,ASN_37153_SYC,ASN_37150_ZAF,ASN_37399_ZAF,ASN_13335_REU,ASN_13335_ZAF,ASN_13335_RWA,ASN_13335_DJI,ASN_13335_MAR,ASN_13335_NGA,ASN_13335_TZA,ASN_13335_KEN,ASN_13335_MDG,ASN_13335_AGO,ASN_13335_MUS,ASN_37542_ZAF,ASN_37314_ZAF,ASN_37678_BWA,ASN_36916_ZAF,ASN_36916_BEN,ASN_4809_NGA,ASN_4809_ZAF,ASN_4809_KEN,ASN_36968_ZAF,ASN_32437_ZAF,ASN_327849_ZAF,ASN_327733_ZAF,ASN_49544_ZAF,ASN_327813_GHA,ASN_327813_ZAF,ASN_327813_NGA,ASN_327813_KEN,ASN_327813_SYC,ASN_327817_ZAF,ASN_37049_ZAF,ASN_37663_ZAF,ASN_37199_ZAF,ASN_37333_ZAF,ASN_37457_ZAF,ASN_37497_ZAF,ASN_327693_ZAF,ASN_37519_ZAF,ASN_37187_MWI,ASN_3491_ZAF,ASN_3491_KEN,ASN_3491_TZA,ASN_3491_MOZ,ASN_3491_ZMB,ASN_3491_TUN,ASN_42473_ZAF,ASN_3300_ZAF,ASN_37468_AGO,ASN_21351_REU,ASN_37439_ZAF,ASN_327826_ZAF,ASN_37564_ZAF,ASN_327824_ZAF,ASN_37363_ZAF,ASN_41095_SYC,ASN_327893_ZAF,ASN_8075_ZAF,ASN_37358_ZAF,ASN_327754_ZAF,ASN_37254_ZAF,ASN_37403_ZAF,ASN_25818_ZAF,ASN_25818_KEN,ASN_36994_ZAF,ASN_36994_AGO,ASN_36994_NGA,ASN_37009_NAM,ASN_37599_ZAF,ASN_37618_ZAF,ASN_327804_ZAF,ASN_36944_ZAF,ASN_37662_DJI,ASN_37662_NGA,ASN_37662_TZA,ASN_37662_ZAF,ASN_37662_MUS,ASN_37662_KEN,ASN_37662_SOM,ASN_37662_ZWE,ASN_327698_ZAF,ASN_327750_COD,ASN_327750_ZAF,ASN_32934_ZAF,ASN_2635_ZAF,ASN_23889_MUS,ASN_23889_ZAF,ASN_54113_ZAF,ASN_37680_ZAF,ASN_36692_ZAF,ASN_15133_ZAF,ASN_10310_ZAF,ASN_37697_MOZ,ASN_327767_ZAF,ASN_19551_ZAF,ASN_54994_ZAF,ASN_16509_ZAF,ASN_37054_MDG,ASN_62597_ZAF,ASN_36236_ZAF,ASN_37302_ZAF,ASN_714_ZAF,ASN_36951_ZAF,ASN_199524_ZAF,ASN_37239_ZAF,ASN_37239_BDI,ASN_1828_ZAF,ASN_60171_MLI,ASN_60171_GHA,ASN_60171_BFA,ASN_60171_NGA,ASN_37451_COG,ASN_327822_ZAF,ASN_30999_MUS,ASN_37691_ZAF,ASN_15706_SDN,ASN_15706_TCD,ASN_33788_SDN,ASN_11259_AGO,ASN_37011_AGO,ASN_37645_AGO,ASN_15399_KEN,ASN_15399_TZA,ASN_15399_UGA,ASN_15399_NGA,ASN_36866_KEN,ASN_15808_KEN,ASN_12455_KEN,ASN_33771_KEN,ASN_36914_KEN,ASN_37273_UGA,ASN_36915_KEN,ASN_36948_KEN,ASN_37578_KEN,ASN_37684_KEN,ASN_37684_TZA,ASN_37305_KEN,ASN_37027_KEN,ASN_37027_UGA,ASN_37027_TZA,ASN_37109_KEN,ASN_327906_KEN,ASN_37386_UGA,ASN_37063_UGA,ASN_37113_UGA,ASN_327687_UGA,ASN_37006_RWA,ASN_37006_MUS,ASN_327707_RWA,ASN_36868_MUS,ASN_37204_ZWE,ASN_37582_GAB,ASN_37125_NGA,ASN_37613_NGA,ASN_37613_GHA,ASN_37521_NGA,ASN_21859_ZAF,ASN_21859_NGA,ASN_22822_ZAF,ASN_36932_NGA,ASN_37182_TZA,ASN_37013_TZA,ASN_33765_TZA,ASN_36908_TZA,ASN_37133_TZA,ASN_37133_SYC,ASN_36965_TZA,ASN_37101_TZA,ASN_36930_TZA,ASN_37035_TZA,ASN_37362_TZA,ASN_327728_TZA,ASN_327692_TZA,ASN_327885_TZA"},{"id":"IXP_93","name":"Ghana Internet Exchange","country":"GHA","latitude":6.789989804244834,"longitude":0.620550697516172,"customers":"ASN_30986_GHA,ASN_37012_GHA,ASN_33786_GHA,ASN_37103_GHA,ASN_29614_GHA,ASN_29614_BFA,ASN_37087_GHA,ASN_37030_GHA,ASN_37623_GHA,ASN_37613_NGA,ASN_37613_GHA,ASN_4809_NGA,ASN_4809_ZAF,ASN_4809_KEN,ASN_42_ZAF,ASN_42_TUN,ASN_20940_ZAF"},{"id":"IXP_765","name":"Rwanda Internet exchange","country":"RWA","latitude":-1.3197520878894275,"longitude":30.37258662791144,"customers":"ASN_37006_RWA,ASN_37006_MUS,ASN_327707_RWA,ASN_30844_MUS,ASN_30844_ZMB,ASN_30844_KEN,ASN_30844_TZA,ASN_30844_UGA,ASN_30844_ZAF,ASN_30844_ZWE,ASN_30844_RWA,ASN_30844_COD,ASN_37100_KEN,ASN_37100_MUS,ASN_37100_TZA,ASN_37100_ZAF,ASN_21174_RWA,ASN_37228_RWA,ASN_37547_RWA,ASN_36890_RWA,ASN_37124_RWA,ASN_37177_ZAF,ASN_37181_ZAF,ASN_42_ZAF,ASN_42_TUN,ASN_22690_RWA,ASN_37619_RWA"},{"id":"IXP_932","name":"Angola Internet Exchange","country":"AGO","latitude":-7.066936372314626,"longitude":13.122166199206765,"customers":"ASN_327775_AGO,ASN_11259_AGO,ASN_17400_AGO,ASN_36881_AGO,ASN_36907_AGO,ASN_37081_AGO,ASN_37119_AGO,ASN_37384_AGO,ASN_327806_AGO,ASN_33763_NAM,ASN_33763_AGO,ASN_33763_MOZ,ASN_37645_AGO,ASN_42_ZAF,ASN_42_TUN,ASN_327833_AGO"},{"id":"IXP_59","name":"Cairo Internet Exchange","country":"EGY","latitude":31.171551812345584,"longitude":30.153976155555767,"customers":""},{"id":"IXP_367","name":"Botswana Internet Exchange","country":"BWA","latitude":-22.56288300607126,"longitude":25.359055149770057,"customers":"ASN_33781_BWA,ASN_37711_BWA"},{"id":"IXP_156","name":"Mauritius Internet Exchange","country":"MUS","latitude":-20.24435,"longitude":57.49175,"customers":"ASN_42_ZAF,ASN_42_TUN,ASN_36868_MUS,ASN_30999_MUS,ASN_23889_MUS,ASN_23889_ZAF,ASN_51110_REU,ASN_51110_MYT,ASN_37455_MUS,ASN_37622_MUS"},{"id":"IXP_547","name":"Zambia Internet Exchange Point","country":"ZMB","latitude":-16.510355271085032,"longitude":27.160723841055642,"customers":""},{"id":"IXP_606","name":"TIX Tanzania - Arusha","country":"TZA","latitude":-5.864681342643031,"longitude":37.501039581009245,"customers":"ASN_33791_TZA,ASN_30844_MUS,ASN_30844_ZMB,ASN_30844_KEN,ASN_30844_TZA,ASN_30844_UGA,ASN_30844_ZAF,ASN_30844_ZWE,ASN_30844_RWA,ASN_30844_COD,ASN_37084_TZA,ASN_37143_TZA,ASN_42_ZAF,ASN_42_TUN,ASN_327885_TZA,ASN_36908_TZA,ASN_33765_TZA,ASN_37133_TZA,ASN_37133_SYC,ASN_36930_TZA,ASN_36909_TZA"},{"id":"IXP_1312","name":"Sudan Internet Exchange Point","country":"SDN","latitude":15.654068600846712,"longitude":34.23818577232304,"customers":"ASN_15706_SDN,ASN_15706_TCD,ASN_33788_SDN,ASN_36998_SDN,ASN_36972_SDN,ASN_37211_SDN,ASN_42_ZAF,ASN_42_TUN"},{"id":"IXP_158","name":"Mozambique Internet Exchange","country":"MOZ","latitude":-24.45266646737368,"longitude":33.424245467649115,"customers":"ASN_31960_MOZ,ASN_42235_MOZ,ASN_30619_MOZ,ASN_32017_MOZ,ASN_36865_MOZ,ASN_37110_MOZ,ASN_37223_MOZ,ASN_37223_ZAF,ASN_37342_MOZ,ASN_37489_MOZ,ASN_3491_ZAF,ASN_3491_KEN,ASN_3491_TZA,ASN_3491_MOZ,ASN_3491_ZMB,ASN_3491_TUN,ASN_37556_MOZ,ASN_37697_MOZ,ASN_327700_MOZ"},{"id":"IXP_1029","name":"Malawi IXP","country":"MWI","latitude":-16.109414479022202,"longitude":35.119027644669806,"customers":"ASN_37187_MWI,ASN_36969_MWI,ASN_37098_MWI,ASN_37294_MWI,ASN_37440_MWI"},{"id":"IXP_593","name":"Middle East Internet eXchange","country":"EGY","latitude":28.955178778808296,"longitude":31.937562816202835,"customers":""},{"id":"IXP_60","name":"Cairo Regional Internet Exchange","country":"EGY","latitude":28.838204857005145,"longitude":30.739436476414475,"customers":""},{"id":"IXP_173","name":"Ibadan Internet Exchange","country":"NGA","latitude":7.371953854923969,"longitude":4.313276602471917,"customers":""},{"id":"IXP_207","name":"Hub","country":"ZAF","latitude":-34.08933814743611,"longitude":19.016591376855924,"customers":""},{"id":"IXP_208","name":"Grahamstown Internet Exchange","country":"ZAF","latitude":-26.42681918734097,"longitude":26.4351377959663,"customers":""},{"id":"IXP_210","name":"South African Internet Exchange","country":"ZAF","latitude":-27.45211881381749,"longitude":27.78228362532857,"customers":""},{"id":"IXP_220","name":"Swaziland Internet Exchange","country":"SWZ","latitude":-25.81794148223433,"longitude":31.027871658030964,"customers":""},{"id":"IXP_364","name":"Zimbabwe Internet Exchange","country":"ZWE","latitude":-16.447222957581968,"longitude":30.37166564295646,"customers":""},{"id":"IXP_545","name":"Ponto de Intercambio Internet Angola","country":"AGO","latitude":-9.868429809980217,"longitude":13.258997783980352,"customers":"ASN_327775_AGO,ASN_11259_AGO,ASN_17400_AGO,ASN_36881_AGO,ASN_36907_AGO,ASN_37081_AGO,ASN_37119_AGO,ASN_37384_AGO,ASN_327806_AGO,ASN_33763_NAM,ASN_33763_AGO,ASN_33763_MOZ,ASN_37645_AGO,ASN_42_ZAF,ASN_42_TUN,ASN_327833_AGO"},{"id":"IXP_546","name":"BurundiX Internet Exchange Point","country":"BDI","latitude":-3.8384069537885543,"longitude":30.215834048541765,"customers":""},{"id":"IXP_699","name":"Côte d'Ivoire Internet Exchange Point","country":"CIV","latitude":6.864189780726714,"longitude":-3.613022399706523,"customers":""},{"id":"IXP_1207","name":"AMS-IX East Africa","country":"KEN","latitude":-4.449169389575299,"longitude":39.290570346005254,"customers":""},{"id":"IXP_1303","name":"Lesotho Internet Exchange","country":"LSO","latitude":-29.814296719625208,"longitude":27.262231623774714,"customers":""},{"id":"IXP_1474","name":"Tunisian Internet Exchange Point","country":"TUN","latitude":36.68314220359472,"longitude":8.374414910053968,"customers":"ASN_5438_TUN,ASN_37177_ZAF,ASN_37181_ZAF,ASN_2609_TUN"},{"id":"IXP_1887","name":"Gabon Internet Exchange","country":"GAB","latitude":-1.0156489956228518,"longitude":9.664311479560308,"customers":"ASN_37582_GAB,ASN_16058_GAB,ASN_37390_GAB,ASN_42_ZAF,ASN_42_TUN,ASN_37616_GAB"},{"id":"IXP_1840","name":"NAPAfrica Durban","country":"ZAF","latitude":-28.777685253879984,"longitude":30.88199534774775,"customers":"ASN_37179_ZAF,ASN_36951_ZAF,ASN_37302_ZAF,ASN_36874_ZAF,ASN_37100_KEN,ASN_37100_MUS,ASN_37100_TZA,ASN_37100_ZAF,ASN_10474_ZAF,ASN_37271_ZAF,ASN_37239_ZAF,ASN_37239_BDI,ASN_11845_ZAF,ASN_37519_ZAF,ASN_327733_ZAF,ASN_42_ZAF,ASN_42_TUN,ASN_37457_ZAF,ASN_32437_ZAF,ASN_327849_ZAF,ASN_327817_ZAF,ASN_327824_ZAF,ASN_37314_ZAF,ASN_327754_ZAF,ASN_37254_ZAF,ASN_36916_ZAF,ASN_36916_BEN,ASN_37497_ZAF,ASN_25818_ZAF,ASN_25818_KEN,ASN_327782_ZAF,ASN_13335_REU,ASN_13335_ZAF,ASN_13335_RWA,ASN_13335_DJI,ASN_13335_MAR,ASN_13335_NGA,ASN_13335_TZA,ASN_13335_KEN,ASN_13335_MDG,ASN_13335_AGO,ASN_13335_MUS,ASN_2018_ZAF,ASN_2018_LSO,ASN_327693_ZAF,ASN_37662_DJI,ASN_37662_NGA,ASN_37662_TZA,ASN_37662_ZAF,ASN_37662_MUS,ASN_37662_KEN,ASN_37662_SOM,ASN_37662_ZWE,ASN_36994_ZAF,ASN_36994_AGO,ASN_36994_NGA,ASN_16637_ZAF,ASN_16637_LBR,ASN_16637_MUS,ASN_16637_NAM,ASN_16637_BWA,ASN_16637_ZMB,ASN_37675_ZAF,ASN_22355_ZAF,ASN_33762_ZAF,ASN_37172_ZAF,ASN_37358_ZAF,ASN_37634_ZAF,ASN_37315_ZAF,ASN_327698_ZAF,ASN_327761_ZAF,ASN_37016_ZAF,ASN_37417_ZAF,ASN_327805_ZAF,ASN_61092_ZAF,ASN_37479_ZAF,ASN_37482_ZAF,ASN_37670_ZAF,ASN_3741_ZAF,ASN_3741_SYC,ASN_5713_ZAF,ASN_5713_KEN,ASN_37564_ZAF,ASN_37168_ZAF,ASN_37680_ZAF,ASN_37150_ZAF,ASN_37049_ZAF,ASN_37599_ZAF,ASN_37673_ZAF,ASN_36968_ZAF,ASN_18931_ZAF"},{"id":"IXP_1848","name":"ANGONIX","country":"AGO","latitude":-7.9237809302628905,"longitude":14.29374562117806,"customers":"ASN_37468_AGO,ASN_37645_AGO,ASN_37011_AGO,ASN_37119_AGO,ASN_36907_AGO,ASN_42_ZAF,ASN_42_TUN,ASN_25818_ZAF,ASN_25818_KEN,ASN_327833_AGO,ASN_49544_ZAF,ASN_37603_AGO,ASN_17400_AGO,ASN_11845_ZAF,ASN_36936_AGO,ASN_19711_SWZ,ASN_33763_NAM,ASN_33763_AGO,ASN_33763_MOZ,ASN_11259_AGO,ASN_37366_AGO"},{"id":"IXP_1929","name":"DjIX","country":"DJI","latitude":11.647149302385401,"longitude":42.81295482041084,"customers":""},{"id":"IXP_1839","name":"Burkina Faso IXP","country":"BFA","latitude":11.648735703044641,"longitude":-0.1925128667043019,"customers":""},{"id":"IXP_2075","name":"Asteroid Mombasa","country":"KEN","latitude":-2.257150860294285,"longitude":40.49074201141454,"customers":""},{"id":"IXP_2055","name":"Douala IXP","country":"CMR","latitude":4.599118338899986,"longitude":10.920612452047132,"customers":""},{"id":"IXP_1884","name":"Internet Exchange Point of Nigeria - Abuja","country":"NGA","latitude":8.381786938683096,"longitude":6.189727080543429,"customers":"ASN_30998_NGA,ASN_37662_DJI,ASN_37662_NGA,ASN_37662_TZA,ASN_37662_ZAF,ASN_37662_MUS,ASN_37662_KEN,ASN_37662_SOM,ASN_37662_ZWE,ASN_37480_NGA"},{"id":"IXP_1838","name":"Benin IX","country":"BEN","latitude":6.989092562407857,"longitude":2.4789491223673017,"customers":"ASN_37090_BEN,ASN_28683_BEN,ASN_37424_BEN,ASN_37136_BEN,ASN_37292_BEN"},{"id":"IXP_1811","name":"Serrekunda Internet Exchange Point","country":"GMB","latitude":13.251448068514451,"longitude":-16.092450070423375,"customers":"ASN_327719_GMB,ASN_25250_GMB,ASN_37309_GMB,ASN_37323_GMB,ASN_37503_GMB,ASN_42_ZAF,ASN_42_TUN"},{"id":"IXP_1801","name":"Côte d'Ivoire Internet Exchange Point","country":"CIV","latitude":5.568912500787197,"longitude":-5.432229985232823,"customers":"ASN_36974_CIV,ASN_36974_RWA,ASN_36974_BWA,ASN_36974_NGA,ASN_36974_ZMB,ASN_29571_CIV,ASN_37475_CMR,ASN_37190_CIV,ASN_37381_CIV"},{"id":"IXP_1924","name":"Mombasa Internet Exchange Point","country":"KEN","latitude":-0.15127773451048476,"longitude":40.17115106357854,"customers":"ASN_9129_KEN,ASN_37273_UGA"},{"id":"IXP_1928","name":"Senegal IX","country":"SEN","latitude":13.652190578264438,"longitude":-16.084570852645083,"customers":"ASN_42_ZAF,ASN_42_TUN"},{"id":"IXP_1993","name":"Harare Internet Exchange","country":"ZWE","latitude":-19.38394359529535,"longitude":30.464305048161513,"customers":"ASN_37204_ZWE,ASN_37183_ZAF,ASN_37183_ZWE,ASN_37183_UGA,ASN_30844_MUS,ASN_30844_ZMB,ASN_30844_KEN,ASN_30844_TZA,ASN_30844_UGA,ASN_30844_ZAF,ASN_30844_ZWE,ASN_30844_RWA,ASN_30844_COD,ASN_37184_ZWE,ASN_36986_ZWE,ASN_37123_ZWE,ASN_42_ZAF,ASN_42_TUN"},{"id":"IXP_2070","name":"IXP-GUINEE","country":"GIN","latitude":11.738120559016462,"longitude":-13.132863255429294,"customers":""},{"id":"IXP_2019","name":"Mali IXP","country":"MLI","latitude":13.269954989302978,"longitude":-8.442700243832276,"customers":""},{"id":"IXP_1973","name":"Togo Internet Exchange Point","country":"TGO","latitude":6.287059368278546,"longitude":1.098486797884345,"customers":""},{"id":"IXP_1784","name":"Windhoek IXP","country":"NAM","latitude":-23.018075870669815,"longitude":17.273855691408063,"customers":"ASN_33763_NAM,ASN_33763_AGO,ASN_33763_MOZ,ASN_37009_NAM"},{"id":"IXP_1885","name":"Internet Exchange Point of Nigeria - Port Harcourt","country":"NGA","latitude":6.662124744511807,"longitude":7.8072851160496395,"customers":""},{"id":"IXP_1911","name":"Dodoma Internet Exchange Point","country":"TZA","latitude":-5.075903545683268,"longitude":37.01944411402412,"customers":""},{"id":"IXP_1881","name":"Madagascar Global Internet Exchange","country":"MDG","latitude":-18.708588409941928,"longitude":47.25800577857958,"customers":""},{"id":"IXP_2036","name":"Zanzibar Internet Exchange Point","country":"TZA","latitude":-9.974188749519797,"longitude":38.711977793500445,"customers":""},{"id":"IXP_1952","name":"Cameroon Internet Exchange Point","country":"CMR","latitude":3.1912923243878,"longitude":11.151646791826042,"customers":""},{"id":"IXP_1992","name":"Burundi Internet Exchange Point","country":"BDI","latitude":-4.316142426100804,"longitude":29.58359072930803,"customers":"ASN_327798_BDI,ASN_37545_BDI,ASN_25429_BDI,ASN_37429_BDI,ASN_327720_BDI,ASN_37586_BDI,ASN_327799_BDI,ASN_37336_BDI"},{"id":"IXP_1897","name":"Liberia Internet Exchange Point","country":"LBR","latitude":7.420275442357253,"longitude":-10.146287457291573,"customers":"ASN_37094_LBR,ASN_37203_LBR,ASN_37410_LBR,ASN_37410_UGA"},{"id":"IXP_1912","name":"Mwanza Internet Exchange Point","country":"TZA","latitude":-9.233996440035437,"longitude":33.366402025973834,"customers":""},{"id":"IXP_1541","name":"Congo Brazzaville IX","country":"COG","latitude":-4.180648495342615,"longitude":15.102438577722518,"customers":""},{"id":"IXP_2072","name":"Somali Internet Exchange Point ","country":"SOM","latitude":3.310855662324128,"longitude":44.069025408629315,"customers":""},{"id":"IXP_2145","name":"Tchad Internet Exchange Point ","country":"TCD","latitude":10.311591054729746,"longitude":15.602816062984504,"customers":""},{"id":"IXP_1909","name":"Lubumbashi Internet Exchange","country":"COD","latitude":-11.197098540289689,"longitude":28.265428903085063,"customers":""},{"id":"IXP_1925","name":"Lesotho Internet Exchange Point","country":"LSO","latitude":-28.987301558443942,"longitude":28.344569106109883,"customers":""},{"id":"IXP_1917","name":"Casablanca Internet Exchange","country":"MAR","latitude":31.452896795701474,"longitude":-6.799380340350724,"customers":""},{"id":"IXP_1805","name":"Enfidha Internet Exchange","country":"TUN","latitude":36.40893855389219,"longitude":10.245389918904918,"customers":""},{"id":"IXP_2068","name":"West African Internet Exchange","country":"NGA","latitude":6.747984817623495,"longitude":4.7160101053021215,"customers":""},{"id":"IXP_1574","name":"CG-IX Pointe-Noire","country":"COG","latitude":-3.4562325333516,"longitude":12.152819447957942,"customers":""},{"id":"IXP_1708","name":"Algeria Internet Exchange","country":"DZA","latitude":35.27540500130136,"longitude":3.3728431303419426,"customers":""},{"id":"IXP_1804","name":"Mbabane Internet Exchange","country":"SWZ","latitude":-26.483459055572435,"longitude":31.52970585448227,"customers":""},{"id":"IXP_1843","name":"Seychelles Internet Exchange Point","country":"SYC","latitude":-4.61764,"longitude":55.44766,"customers":""},{"id":"IXP_1886","name":"Internet Exchange Point of Nigeria - Kano","country":"NGA","latitude":10.394813504302256,"longitude":8.096103066792018,"customers":""},{"id":"IXP_1888","name":"Mauritania IX","country":"MRT","latitude":17.579463392836377,"longitude":-14.769580365526691,"customers":""},{"id":"IXP_1904","name":"RIMIX","country":"MRT","latitude":17.674042179428476,"longitude":-15.76363951432853,"customers":""},{"id":"IXP_1910","name":"Goma Internet Exchange","country":"COD","latitude":-0.5456363182944597,"longitude":27.967510586097884,"customers":""},{"id":"IXP_1921","name":"Niger Internet Exchange","country":"NER","latitude":14.372789970380794,"longitude":1.5182247619838627,"customers":""},{"id":"IXP_1955","name":"Maroc Internet Exchange Point","country":"MAR","latitude":32.964571688423455,"longitude":-5.55796697050156,"customers":""}]